promptlint/__init__.py
promptlint/cli.py
promptlint/analyzers/__init__.py
promptlint/analyzers/clarity.py
promptlint/analyzers/cost.py
promptlint/analyzers/security.py
promptlint/core/__init__.py
promptlint/core/analyzer.py
promptlint/core/differ.py
promptlint/core/models.py
promptlint/core/parser.py
promptlint/reporters/__init__.py
promptlint/reporters/console.py
promptlint/reporters/json_reporter.py
promptlint/reporters/markdown.py
promptlint/utils/__init__.py
promptlint/utils/pricing.py
promptlint/utils/tokenizer.py
promptlint-0.1.1.dist-info/licenses/LICENSE
promptlint-0.1.1.dist-info/METADATA
promptlint-0.1.1.dist-info/WHEEL
promptlint-0.1.1.dist-info/entry_points.txt
promptlint-0.1.1.dist-info/top_level.txt
promptlint-0.1.1.dist-info/RECORD
