Metadata-Version: 2.4
Name: promptlint
Version: 0.1.1
Summary: A comprehensive prompt analyzer for LLM optimization, security scanning, and cost estimation
Home-page: https://github.com/fyunusa/promptlint
Author: PromptLint Contributors
Author-email: PromptLint Team <team@promptlint.dev>
License-Expression: MIT
Project-URL: Homepage, https://github.com/yourusername/promptlint
Project-URL: Bug Tracker, https://github.com/yourusername/promptlint/issues
Project-URL: Documentation, https://github.com/yourusername/promptlint#readme
Keywords: prompt,linting,analysis,optimization,security,cost,estimation
Classifier: Development Status :: 4 - Beta
Classifier: Environment :: Console
Classifier: Intended Audience :: Developers
Classifier: Natural Language :: English
Classifier: Operating System :: OS Independent
Classifier: Programming Language :: Python :: 3
Classifier: Programming Language :: Python :: 3.11
Classifier: Programming Language :: Python :: 3.12
Classifier: Topic :: Software Development :: Libraries :: Python Modules
Classifier: Topic :: Text Processing :: Linguistic
Requires-Python: >=3.11
License-File: LICENSE
Requires-Dist: typer>=0.9.0
Requires-Dist: rich>=13.7.0
Requires-Dist: pydantic>=2.5.0
Requires-Dist: PyYAML>=6.0
Requires-Dist: tiktoken>=0.5.0
Provides-Extra: dev
Requires-Dist: pytest>=7.4.0; extra == "dev"
Requires-Dist: pytest-cov>=4.1.0; extra == "dev"
Requires-Dist: black>=23.12.0; extra == "dev"
Requires-Dist: ruff>=0.1.0; extra == "dev"
Requires-Dist: mypy>=1.7.0; extra == "dev"
Dynamic: author
Dynamic: home-page
Dynamic: license-file
Dynamic: requires-python
